gym_twolinkarm_env/__init__.py
gym_twolinkarm_env/envs/base.py
gym_twolinkarm_env/envs/func.py
gym_twolinkarm_env/envs/gravity.py
gym_twolinkarm_env/envs/gravity_bottom.py
gym_twolinkarm_env/envs/gravity_random.py
gym_twolinkarm_env/envs/nogravity.py
gym_twolinkarm_env/envs/normal.py
gym_twolinkarm_env/envs/normal_random.py
gym_twolinkarm_env/envs/assets/__init__.py
gym_twolinkarm_env/envs/assets/clockwise.png
twolinkarm/__init__.py
gym_twolinkarm_env-0.1.10.dist-info/LICENSE
gym_twolinkarm_env-0.1.10.dist-info/METADATA
gym_twolinkarm_env-0.1.10.dist-info/WHEEL
gym_twolinkarm_env-0.1.10.dist-info/top_level.txt
gym_twolinkarm_env-0.1.10.dist-info/RECORD
