Metadata-Version: 2.1
Name: gym-twolinkarm-env
Version: 0.1.10
Summary: This is the open-ai-gym environment for controlling two link arm
Home-page: https://github.com/gyuta/gym-twolinkarm-env
Author: gyuta
License: UNKNOWN
Project-URL: Bug Tracker, https://github.com/gyuta/gym-twolinkarm-env/issues
Platform: UNKNOWN
Classifier: Programming Language :: Python :: 3
Classifier: License :: OSI Approved :: MIT License
Classifier: Operating System :: OS Independent
Requires-Python: >=3.6
License-File: LICENSE
Requires-Dist: gym
Requires-Dist: scipy
Requires-Dist: pyglet
